{"hash":"5ee00dc0b71878963f9b5fb39ff7b4fecc0fc2a1","data":{"posts":{"pageInfo":{"totalPages":27,"currentPage":23},"edges":[{"node":{"id":"2789a28cea8d9db34303eb0ac813a357","title":"Hướng dẫn sử dụng thuộc tính counter-reset và counter-increment","date":"2018-05-21","timeToRead":1,"desc":"Nếu muốn đánh số tự động trong css, ta thường sử dụng đến kiểu display list-style, bài này giới thiệu một thuộc tính khác ít ai biết tới","cover_image":"","path":"/huong-dan-su-dung-thuoc-tinh-counter-reset-va-counter-increment/","tags":[{"id":"css","title":"css","path":"/tag/css/"}]}},{"node":{"id":"d63cff185db98b9e7840ee8d3f1c1191","title":"Giải thích async/await của javascript","date":"2018-05-07","timeToRead":6,"desc":"Hướng dẫn các bạn nắm vững async/await trong javascript, kèm ví dụ cụ thể","cover_image":"","path":"/giai-thich-async-await-cua-javascript/","tags":[{"id":"javascript","title":"javascript","path":"/tag/javascript/"}]}},{"node":{"id":"c739028abbcb89e9d3e7c89db87fa879","title":"Transition trong React Native với React Navigation","date":"2018-05-02","timeToRead":3,"desc":"Hướng dẫn làm transition trong React Native với react navigation","cover_image":"","path":"/transition-trong-react-native-voi-react-navigation/","tags":[{"id":"javascript","title":"javascript","path":"/tag/javascript/"},{"id":"react","title":"react","path":"/tag/react/"},{"id":"react-native","title":"react-native","path":"/tag/react-native/"}]}},{"node":{"id":"ed20ea853375e5181c942b2bd43f7653","title":"Cải thiện performance của React App","date":"2018-05-01","timeToRead":7,"desc":"Trong bài này, chúng ta cùng đi qua các bước để fix những issue liên quan đến performance thường thấy.","cover_image":"","path":"/cai-thien-performance-cua-react-app/","tags":[{"id":"javascript","title":"javascript","path":"/tag/javascript/"},{"id":"react","title":"react","path":"/tag/react/"},{"id":"performance","title":"performance","path":"/tag/performance/"}]}},{"node":{"id":"819a9c7b235ca822b9ba12c248406cf3","title":"Google Maps và React","date":"2018-04-27","timeToRead":3,"desc":"Hướng Sử dụng google maps api trong React","cover_image":"","path":"/google-maps-va-react/","tags":[{"id":"javascript","title":"javascript","path":"/tag/javascript/"},{"id":"react","title":"react","path":"/tag/react/"}]}},{"node":{"id":"038bc8dd6494a9d7ff4a2ffd06cb8a36","title":"Một số cách làm Animation trong React","date":"2018-04-24","timeToRead":8,"desc":"Tổng hợp một số phương pháp làm animation với React","cover_image":"","path":"/mot-so-cach-lam-animation-trong-react/","tags":[{"id":"javascript","title":"javascript","path":"/tag/javascript/"},{"id":"react","title":"react","path":"/tag/react/"}]}},{"node":{"id":"6f0a36bc96e70468240bed06d352fce7","title":"Giải thích Observer Pattern trong javascript","date":"2018-04-17","timeToRead":3,"desc":"Observer là một pattern khá phổ biến trong javascript, bài giải thích ngắn gọn về pattern này","cover_image":"","path":"/giai-thich-observer-pattern-trong-javascript/","tags":[{"id":"javascript","title":"javascript","path":"/tag/javascript/"},{"id":"react","title":"react","path":"/tag/react/"}]}},{"node":{"id":"1791be0a9e147d1a847171d0eaedb2be","title":"Giới thiệu Expo, nhập môn React Native","date":"2018-04-16","timeToRead":3,"desc":"Để bắt đầu với React Native, cách nhanh nhất không cần cài Android Studio, Xcode có ngay môi trường để chạy test React Native thì Expo chính là cái bạn cần","cover_image":"","path":"/gioi-thieu-expo-nhap-mon-react-native/","tags":[{"id":"javascript","title":"javascript","path":"/tag/javascript/"},{"id":"react","title":"react","path":"/tag/react/"},{"id":"react-native","title":"react-native","path":"/tag/react-native/"}]}},{"node":{"id":"05c193d3b678d4c4e765c0a2c85ccb2d","title":"Chém gió: Tại sao tui vẫn thích Firefox","date":"2018-04-05","timeToRead":3,"desc":"Không biết bạn sinh ra từ thuở nào, nhưng tui là thế hệ 8x, thời điểm mà Firefox nổi lên - rồi chìm xuống","cover_image":"https://cdn-images-1.medium.com/max/1000/1*Gd9wkMJQxrCi8UNZWRgx-Q.png","path":"/chem-gio-tai-sao-tui-van-thich-firefox/","tags":[{"id":"ux-ui","title":"ux-ui","path":"/tag/ux-ui/"},{"id":"dam-dao","title":"dam-dao","path":"/tag/dam-dao/"}]}},{"node":{"id":"8eedc3591fcf6d3c79f1d05a3ad61ae6","title":"Danh sách đồ chơi để bắt đầu với React Native","date":"2018-04-04","timeToRead":3,"desc":"Để bắt đầu và đào sâu vọc vạch với React Native, bạn sẽ cần đụng tới những món đồ chơi sau","cover_image":"","path":"/danh-sach-do-choi-de-bat-dau-voi-react-native/","tags":[{"id":"javascript","title":"javascript","path":"/tag/javascript/"},{"id":"react","title":"react","path":"/tag/react/"},{"id":"react-native","title":"react-native","path":"/tag/react-native/"}]}}]}},"context":{}}